remote_auto_fetch/__init__.py
remote_auto_fetch/file_md5.py
remote_auto_fetch/main.py
remote_auto_fetch-0.1.3.dist-info/LICENSE
remote_auto_fetch-0.1.3.dist-info/METADATA
remote_auto_fetch-0.1.3.dist-info/WHEEL
remote_auto_fetch-0.1.3.dist-info/RECORD
