Metadata-Version: 2.3
Name: remote-auto-fetch
Version: 0.1.3
Summary: Fetch something from url if not exists.
License: MIT
Author: GGN_2015
Author-email: premierbob@qq.com
Requires-Python: >=3.10
Classifier: License :: OSI Approved :: MIT License
Classifier: Programming Language :: Python :: 3
Classifier: Programming Language :: Python :: 3.10
Classifier: Programming Language :: Python :: 3.11
Classifier: Programming Language :: Python :: 3.12
Classifier: Programming Language :: Python :: 3.13
